MANIFEST.in
README.md
requirements.txt
setup.cfg
setup.py
basea/__init__.py
basea/basea_imp.py
basea.egg-info/PKG-INFO
basea.egg-info/SOURCES.txt
basea.egg-info/dependency_links.txt
basea.egg-info/top_level.txt