Metadata-Version: 2.1
Name: basea
Version: 0.4.1
Summary: encoding scheme for converting between small integers and names which would be appropriate for 260-foot tall, giant-monster-punching robots
Home-page: https://github.com/JohnEarnest/Base-A
Author: TnL Community
Author-email: community@todandlorna.com
License: MIT
Platform: UNKNOWN
Classifier: Development Status :: 5 - Production/Stable
Classifier: Programming Language :: Python
Classifier: License :: OSI Approved :: MIT License
Classifier: Operating System :: OS Independent
Classifier: Topic :: Religion
Classifier: Topic :: Utilities
